README.rst
setup.py
tasklocals/__init__.py
tasklocals.egg-info/PKG-INFO
tasklocals.egg-info/SOURCES.txt
tasklocals.egg-info/dependency_links.txt
tasklocals.egg-info/top_level.txt