Metadata-Version: 1.1
Name: tasklocals
Version: 0.2
Summary: Task locals for Tulip/asyncio
Home-page: UNKNOWN
Author: Vladimir Kryachko
Author-email: v.kryachko@gmail.com
License: UNKNOWN
Platform: UNKNOWN
Classifier: Programming Language :: Python
Classifier: Programming Language :: Python :: 3
Classifier: Programming Language :: Python :: 3.3
Classifier: Programming Language :: Python :: 3.4
